epicsapps/__init__.py
epicsapps/apps.py
epicsapps/version.py
epicsapps/areadetector/__init__.py
epicsapps/areadetector/ad_config.py
epicsapps/areadetector/ad_display.py
epicsapps/areadetector/ad_scandbcallback.py
epicsapps/areadetector/calibration_dialog.py
epicsapps/areadetector/contrast_control.py
epicsapps/areadetector/debugtime.py
epicsapps/areadetector/imagepanel.py
epicsapps/areadetector/imageview.py
epicsapps/areadetector/pvconfig.py
epicsapps/areadetector/xrd_integrator.py
epicsapps/icons/areadetector.icns
epicsapps/icons/areadetector.ico
epicsapps/icons/camera.icns
epicsapps/icons/camera.ico
epicsapps/icons/instrument.icns
epicsapps/icons/instrument.ico
epicsapps/icons/logging.icns
epicsapps/icons/logging.ico
epicsapps/icons/microscope.icns
epicsapps/icons/microscope.ico
epicsapps/icons/motorapp.ico
epicsapps/icons/stripchart.icns
epicsapps/icons/stripchart.ico
epicsapps/instruments/InstrumentApp.py
epicsapps/instruments/__init__.py
epicsapps/instruments/configfile.py
epicsapps/instruments/creator.py
epicsapps/instruments/editframe.py
epicsapps/instruments/epics_server.py
epicsapps/instruments/instrument.py
epicsapps/instruments/instrumentpanel.py
epicsapps/instruments/pvconnector.py
epicsapps/instruments/settingsframe.py
epicsapps/instruments/simpledb.py
epicsapps/instruments/test.py
epicsapps/instruments/upgrades.py
epicsapps/instruments/utils.py
epicsapps/ionchamber/__init__.py
epicsapps/ionchamber/ionchamber.py
epicsapps/ionchamber/iocApp/IonChamber.adl
epicsapps/ionchamber/iocApp/IonChamber.db
epicsapps/ionchamber/iocApp/IonChamber.req
epicsapps/ionchamber/iocApp/st.cmd
epicsapps/microscope/__init__.py
epicsapps/microscope/calibrationframe.py
epicsapps/microscope/configfile.py
epicsapps/microscope/controlpanel.py
epicsapps/microscope/fly2_camera.py
epicsapps/microscope/html2pos.py
epicsapps/microscope/icons.py
epicsapps/microscope/imageframe.py
epicsapps/microscope/imagepanel_base.py
epicsapps/microscope/imagepanel_epicsAD.py
epicsapps-2026.1.0.dist-info/licenses/LICENSE
epicsapps-2026.1.0.dist-info/METADATA
epicsapps-2026.1.0.dist-info/WHEEL
epicsapps-2026.1.0.dist-info/entry_points.txt
epicsapps-2026.1.0.dist-info/top_level.txt
epicsapps-2026.1.0.dist-info/RECORD
