Metadata-Version: 2.4
Name: epicsapps
Version: 2026.1.0
Summary: A collection of applications using PyEpics
Author-email: Matthew Newville <newville@cars.uchicago.edu>
Project-URL: Homepage,  https://github.com/pyepics/epicsapps
Project-URL: Documentation, https://pyepics.github.io/epicsapps/
Project-URL: Tracker, https://github.com/pyepics/epicsapps/issues
Keywords: epics,experimental data acquistion
Classifier: Development Status :: 5 - Production/Stable
Classifier: Intended Audience :: Developers
Classifier: Operating System :: OS Independent
Classifier: Programming Language :: Python :: 3.10
Classifier: Programming Language :: Python :: 3.11
Classifier: Programming Language :: Python :: 3.12
Classifier: Programming Language :: Python :: 3.13
Classifier: Programming Language :: Python :: 3.14
Requires-Python: >=3.10
License-File: LICENSE
Requires-Dist: pyepics
Requires-Dist: sqlalchemy
Requires-Dist: psycopg2-binary
Requires-Dist: pyyaml
Requires-Dist: numpy
Requires-Dist: matplotlib
Requires-Dist: pytz
Requires-Dist: datetime
Requires-Dist: python-dateutil
Requires-Dist: wxpython>=4.2.1
Requires-Dist: wxmplot>=2025.1.5
Requires-Dist: wxutils
Requires-Dist: lmfit
Requires-Dist: pyshortcuts>=1.9.5
Requires-Dist: xraydb
Requires-Dist: tabulate
Requires-Dist: transformations
Requires-Dist: toml
Requires-Dist: tomli
Requires-Dist: opencv-python
Provides-Extra: dev
Requires-Dist: build; extra == "dev"
Requires-Dist: twine; extra == "dev"
Provides-Extra: doc
Requires-Dist: Sphinx; extra == "doc"
Requires-Dist: sphinx-copybutton; extra == "doc"
Requires-Dist: sphinxcontrib-video; extra == "doc"
Requires-Dist: numpydoc; extra == "doc"
Provides-Extra: test
Requires-Dist: pytest; extra == "test"
Requires-Dist: pytest-cov; extra == "test"
Requires-Dist: coverage; extra == "test"
Provides-Extra: all
Requires-Dist: epicsapps[dev,doc,test]; extra == "all"
Dynamic: license-file
